geo_activity_playground/__init__.py
geo_activity_playground/__main__.py
geo_activity_playground/alembic/README
geo_activity_playground/alembic/env.py
geo_activity_playground/alembic/script.py.mako
geo_activity_playground/alembic/versions/0163a57011d8_relax_unique_contraints.py
geo_activity_playground/alembic/versions/0f02b92c4f94_add_tag_color.py
geo_activity_playground/alembic/versions/10021d238ada_add_explorer_tile_bookmarks.py
geo_activity_playground/alembic/versions/21967c9ccd81_add_search_query_history.py
geo_activity_playground/alembic/versions/38882503dc7c_add_tags_to_activities.py
geo_activity_playground/alembic/versions/451e7836b53d_add_square_planner_bookmark.py
geo_activity_playground/alembic/versions/63d3b7f6f93c_initial_version.py
geo_activity_playground/alembic/versions/73bf4cd0eded_add_segmentcheck.py
geo_activity_playground/alembic/versions/85fe0348e8a2_add_time_series_uuid_field.py
geo_activity_playground/alembic/versions/93cc82ad1b60_add_parametricplotspec.py
geo_activity_playground/alembic/versions/9cf4b4d4c9da_add_replaced_by.py
geo_activity_playground/alembic/versions/ab83b9d23127_add_upstream_id.py
geo_activity_playground/alembic/versions/b03491c593f6_add_crop_indices.py
geo_activity_playground/alembic/versions/b74f5a37cff9_add_segments.py
geo_activity_playground/alembic/versions/b7d63e7cd0de_add_tile_history_to_db.py
geo_activity_playground/alembic/versions/da2cba03b71d_add_photos.py
geo_activity_playground/alembic/versions/dc8073871da7_add_plotspec_group_by.py
geo_activity_playground/alembic/versions/e02e27876deb_add_square_planner_bookmark_name.py
geo_activity_playground/alembic/versions/eecb7ba15f7e_improve_segments.py
geo_activity_playground/alembic/versions/f2f50843be2d_make_all_fields_in_activity_nullable.py
geo_activity_playground/alembic/versions/script.py.mako
geo_activity_playground/core/__init__.py
geo_activity_playground/core/activities.py
geo_activity_playground/core/config.py
geo_activity_playground/core/coordinates.py
geo_activity_playground-1.20.0.dist-info/LICENSE
geo_activity_playground-1.20.0.dist-info/METADATA
geo_activity_playground-1.20.0.dist-info/WHEEL
geo_activity_playground-1.20.0.dist-info/entry_points.txt
geo_activity_playground-1.20.0.dist-info/RECORD
