Metadata-Version: 2.3
Name: geo-activity-playground
Version: 1.20.0
Summary: Analysis of geo data activities like rides, runs or hikes.
License: MIT
Author: Martin Ueding
Author-email: mu@martin-ueding.de
Requires-Python: >=3.12,<3.15
Classifier: License :: OSI Approved :: MIT License
Classifier: Programming Language :: Python :: 3
Classifier: Programming Language :: Python :: 3.12
Classifier: Programming Language :: Python :: 3.13
Requires-Dist: Pillow (>=11.0.0,<12.0.0)
Requires-Dist: alembic (>=1.15.2,<2.0.0)
Requires-Dist: altair (>=6.0.0,<7.0.0)
Requires-Dist: appdirs (>=1.4.4,<2.0.0)
Requires-Dist: charset-normalizer (>=3.3.2,<4.0.0)
Requires-Dist: coloredlogs (>=15.0.1,<16.0.0)
Requires-Dist: exifread (>=3.2.0,<4.0.0)
Requires-Dist: fitdecode (>=0.10.0,<0.11.0)
Requires-Dist: flask (>=3.0.0,<4.0.0)
Requires-Dist: flask-alembic (>=3.1.1,<4.0.0)
Requires-Dist: flask-babel (>=4.0.0,<5.0.0)
Requires-Dist: flask-sqlalchemy (>=3.1.1,<4.0.0)
Requires-Dist: geojson (>=3.0.1,<4.0.0)
Requires-Dist: gpxpy (>=1.5.0,<2.0.0)
Requires-Dist: jinja2 (>=3.1.2,<4.0.0)
Requires-Dist: matplotlib (>=3.10.1,<4.0.0)
Requires-Dist: numpy (>=2.2.3,<3.0.0)
Requires-Dist: openpyxl (>=3.1.5,<4.0.0)
Requires-Dist: pandas (>=2.2.3,<3.0.0)
Requires-Dist: pyarrow (>=22.0.0,<23.0.0)
Requires-Dist: python-dateutil (>=2.8.2,<3.0.0)
Requires-Dist: requests (>=2.28.1,<3.0.0)
Requires-Dist: shapely (>=2.0.5,<3.0.0)
Requires-Dist: sqlalchemy (>=2.0.40,<3.0.0)
Requires-Dist: stravalib (>=2.0,<3.0)
Requires-Dist: tcxreader (>=0.4.5,<0.5.0)
Requires-Dist: timezonefinder (>=6.5.9,<7.0.0)
Requires-Dist: tomli (>=2.0.1,<3.0.0) ; python_version < "3.11"
Requires-Dist: tqdm (>=4.64.0,<5.0.0)
Requires-Dist: vegafusion (>=2.0.3)
Requires-Dist: vl-convert-python (>=1.0.1,<2.0.0)
Requires-Dist: xmltodict (>=0.13.0,<0.14.0)
